[{"customer_id": "C1", "loyalty_score": 7, "purchase_count": 1, "product_id": ["P29"], "product_category": ["easy peeler"]}, {"customer_id": "C7", "loyalty_score": 3, "purchase_count": 2, "product_id": ["P36", "P37"], "product_category": ["salted caramel dark chocolate", "gummy bears"]}, {"customer_id": "C17", "loyalty_score": 2, "purchase_count": 3, "product_id": ["P14", "P16", "P16"], "product_category": ["women's shoes", "men's belt", "men's belt"]}, {"customer_id": "C22", "loyalty_score": 1, "purchase_count": 3, "product_id": ["P29", "P33", "P29"], "product_category": ["easy peeler", "apples", "easy peeler"]}, {"customer_id": "C23", "loyalty_score": 10, "purchase_count": 1, "product_id": ["P15"], "product_category": ["jumper"]}, {"customer_id": "C26", "loyalty_score": 1, "purchase_count": 3, "product_id": ["P59", "P55", "P48"], "product_category": ["chicken stock", "lentil soup", "tuna"]}, {"customer_id": "C27", "loyalty_score": 10, "purchase_count": 3, "product_id": ["P17", "P21", "P13"], "product_category": ["women's black socks", "women's red dress", "men's dark green trousers"]}, {"customer_id": "C32", "loyalty_score": 3, "purchase_count": 3, "product_id": ["P46", "P53", "P60"], "product_category": ["activated charcoal croissant", "peanut butter", "water"]}, {"customer_id": "C33", "loyalty_score": 5, "purchase_count": 3, "product_id": ["P53", "P45", "P45"], "product_category": ["peanut butter", "hummus", "hummus"]}, {"customer_id": "C36", "loyalty_score": 5, "purchase_count": 1, "product_id": ["P22"], "product_category": ["avocado"]}, {"customer_id": "C39", "loyalty_score": 2, "purchase_count": 1, "product_id": ["P06"], "product_category": ["fabric softener"]}, {"customer_id": "C57", "loyalty_score": 2, "purchase_count": 2, "product_id": ["P31", "P26"], "product_category": ["lemon grass", "broccoli"]}, {"customer_id": "C60", "loyalty_score": 10, "purchase_count": 1, "product_id": ["P63"], "product_category": ["cognac"]}, {"customer_id": "C71", "loyalty_score": 8, "purchase_count": 2, "product_id": ["P38", "P37"], "product_category": ["kombucha", "gummy bears"]}, {"customer_id": "C72", "loyalty_score": 5, "purchase_count": 2, "product_id": ["P15", "P17"], "product_category": ["jumper", "women's black socks"]}, {"customer_id": "C73", "loyalty_score": 2, "purchase_count": 2, "product_id": ["P50", "P53"], "product_category": ["camembert", "peanut butter"]}, {"customer_id": "C82", "loyalty_score": 9, "purchase_count": 2, "product_id": ["P34", "P31"], "product_category": ["raspberries", "lemon grass"]}, {"customer_id": "C83", "loyalty_score": 8, "purchase_count": 1, "product_id": ["P40"], "product_category": ["irn bru"]}, {"customer_id": "C93", "loyalty_score": 5, "purchase_count": 3, "product_id": ["P28", "P22", "P29"], "product_category": ["grapes", "avocado", "easy peeler"]}, {"customer_id": "C98", "loyalty_score": 7, "purchase_count": 2, "product_id": ["P56", "P60"], "product_category": ["greek yoghurt", "water"]}, {"customer_id": "C99", "loyalty_score": 9, "purchase_count": 2, "product_id": ["P53", "P54"], "product_category": ["peanut butter", "almond milk"]}, {"customer_id": "C103", "loyalty_score": 7, "purchase_count": 3, "product_id": ["P63", "P62", "P63"], "product_category": ["cognac", "gin", "cognac"]}, {"customer_id": "C106", "loyalty_score": 5, "purchase_count": 3, "product_id": ["P51", "P54", "P50"], "product_category": ["pizza", "almond milk", "camembert"]}, {"customer_id": "C112", "loyalty_score": 3, "purchase_count": 1, "product_id": ["P40"], "product_category": ["irn bru"]}, {"customer_id": "C113", "loyalty_score": 5, "purchase_count": 3, "product_id": ["P47", "P49", "P41"], "product_category": ["whole chicken", "smoked salmon", "steak"]}, {"customer_id": "C127", "loyalty_score": 4, "purchase_count": 1, "product_id": ["P32"], "product_category": ["onions"]}, {"customer_id": "C129", "loyalty_score": 7, "purchase_count": 3, "product_id": ["P47", "P49", "P58"], "product_category": ["whole chicken", "smoked salmon", "coconut water"]}]