[{"customer_id": "C5", "loyalty_score": 7, "purchase_count": 3, "product_id": ["P41", "P50", "P47"], "product_category": ["steak", "camembert", "whole chicken"]}, {"customer_id": "C11", "loyalty_score": 4, "purchase_count": 1, "product_id": ["P31"], "product_category": ["lemon grass"]}, {"customer_id": "C16", "loyalty_score": 5, "purchase_count": 1, "product_id": ["P63"], "product_category": ["cognac"]}, {"customer_id": "C17", "loyalty_score": 2, "purchase_count": 1, "product_id": ["P46"], "product_category": ["activated charcoal croissant"]}, {"customer_id": "C23", "loyalty_score": 10, "purchase_count": 3, "product_id": ["P57", "P57", "P55"], "product_category": ["parmesan", "parmesan", "lentil soup"]}, {"customer_id": "C25", "loyalty_score": 9, "purchase_count": 1, "product_id": ["P62"], "product_category": ["gin"]}, {"customer_id": "C26", "loyalty_score": 1, "purchase_count": 2, "product_id": ["P45", "P53"], "product_category": ["hummus", "peanut butter"]}, {"customer_id": "C27", "loyalty_score": 10, "purchase_count": 3, "product_id": ["P18", "P19", "P16"], "product_category": ["men's striped socks", "men's trainers", "men's belt"]}, {"customer_id": "C38", "loyalty_score": 7, "purchase_count": 1, "product_id": ["P46"], "product_category": ["activated charcoal croissant"]}, {"customer_id": "C52", "loyalty_score": 1, "purchase_count": 1, "product_id": ["P21"], "product_category": ["women's red dress"]}, {"customer_id": "C53", "loyalty_score": 4, "purchase_count": 1, "product_id": ["P37"], "product_category": ["gummy bears"]}, {"customer_id": "C54", "loyalty_score": 2, "purchase_count": 1, "product_id": ["P62"], "product_category": ["gin"]}, {"customer_id": "C57", "loyalty_score": 2, "purchase_count": 3, "product_id": ["P03", "P10", "P02"], "product_category": ["bin liners", "kitchen knife", "kitchen roll"]}, {"customer_id": "C59", "loyalty_score": 6, "purchase_count": 2, "product_id": ["P35", "P40"], "product_category": ["carrot cake", "irn bru"]}, {"customer_id": "C78", "loyalty_score": 9, "purchase_count": 3, "product_id": ["P28", "P28", "P28"], "product_category": ["grapes", "grapes", "grapes"]}, {"customer_id": "C86", "loyalty_score": 8, "purchase_count": 1, "product_id": ["P58"], "product_category": ["coconut water"]}, {"customer_id": "C88", "loyalty_score": 1, "purchase_count": 1, "product_id": ["P43"], "product_category": ["mince beef"]}, {"customer_id": "C109", "loyalty_score": 6, "purchase_count": 2, "product_id": ["P50", "P46"], "product_category": ["camembert", "activated charcoal croissant"]}, {"customer_id": "C112", "loyalty_score": 3, "purchase_count": 3, "product_id": ["P22", "P33", "P27"], "product_category": ["avocado", "apples", "potatoes"]}, {"customer_id": "C116", "loyalty_score": 5, "purchase_count": 1, "product_id": ["P01"], "product_category": ["detergent"]}, {"customer_id": "C118", "loyalty_score": 7, "purchase_count": 3, "product_id": ["P09", "P02", "P08"], "product_category": ["toilet paper", "kitchen roll", "aluminium foil"]}, {"customer_id": "C125", "loyalty_score": 1, "purchase_count": 1, "product_id": ["P02"], "product_category": ["kitchen roll"]}, {"customer_id": "C130", "loyalty_score": 7, "purchase_count": 3, "product_id": ["P49", "P51", "P54"], "product_category": ["smoked salmon", "pizza", "almond milk"]}, {"customer_id": "C131", "loyalty_score": 4, "purchase_count": 2, "product_id": ["P40", "P37"], "product_category": ["irn bru", "gummy bears"]}]