[{"customer_id": "C3", "loyalty_score": 8, "purchase_count": 3, "product_id": ["P08", "P07", "P01"], "product_category": ["aluminium foil", "cling film", "detergent"]}, {"customer_id": "C8", "loyalty_score": 7, "purchase_count": 1, "product_id": ["P49"], "product_category": ["smoked salmon"]}, {"customer_id": "C13", "loyalty_score": 8, "purchase_count": 3, "product_id": ["P35", "P36", "P38"], "product_category": ["carrot cake", "salted caramel dark chocolate", "kombucha"]}, {"customer_id": "C18", "loyalty_score": 8, "purchase_count": 1, "product_id": ["P20"], "product_category": ["women's blouse"]}, {"customer_id": "C23", "loyalty_score": 10, "purchase_count": 3, "product_id": ["P52", "P52", "P42"], "product_category": ["oats", "oats", "chicken"]}, {"customer_id": "C28", "loyalty_score": 3, "purchase_count": 2, "product_id": ["P38", "P38"], "product_category": ["kombucha", "kombucha"]}, {"customer_id": "C32", "loyalty_score": 3, "purchase_count": 1, "product_id": ["P61"], "product_category": ["red wine"]}, {"customer_id": "C35", "loyalty_score": 7, "purchase_count": 1, "product_id": ["P22"], "product_category": ["avocado"]}, {"customer_id": "C40", "loyalty_score": 4, "purchase_count": 2, "product_id": ["P27", "P29"], "product_category": ["potatoes", "easy peeler"]}, {"customer_id": "C41", "loyalty_score": 9, "purchase_count": 3, "product_id": ["P32", "P28", "P30"], "product_category": ["onions", "grapes", "mango"]}, {"customer_id": "C42", "loyalty_score": 2, "purchase_count": 3, "product_id": ["P44", "P49", "P41"], "product_category": ["milk", "smoked salmon", "steak"]}, {"customer_id": "C46", "loyalty_score": 5, "purchase_count": 1, "product_id": ["P01"], "product_category": ["detergent"]}, {"customer_id": "C52", "loyalty_score": 1, "purchase_count": 1, "product_id": ["P61"], "product_category": ["red wine"]}, {"customer_id": "C57", "loyalty_score": 2, "purchase_count": 1, "product_id": ["P11"], "product_category": ["dishwasher tablets"]}, {"customer_id": "C60", "loyalty_score": 10, "purchase_count": 3, "product_id": ["P61", "P62", "P63"], "product_category": ["red wine", "gin", "cognac"]}, {"customer_id": "C61", "loyalty_score": 4, "purchase_count": 2, "product_id": ["P26", "P29"], "product_category": ["broccoli", "easy peeler"]}, {"customer_id": "C65", "loyalty_score": 2, "purchase_count": 1, "product_id": ["P09"], "product_category": ["toilet paper"]}, {"customer_id": "C69", "loyalty_score": 7, "purchase_count": 3, "product_id": ["P56", "P44", "P57"], "product_category": ["greek yoghurt", "milk", "parmesan"]}, {"customer_id": "C81", "loyalty_score": 7, "purchase_count": 1, "product_id": ["P45"], "product_category": ["hummus"]}, {"customer_id": "C88", "loyalty_score": 1, "purchase_count": 3, "product_id": ["P56", "P57", "P57"], "product_category": ["greek yoghurt", "parmesan", "parmesan"]}, {"customer_id": "C90", "loyalty_score": 3, "purchase_count": 2, "product_id": ["P38", "P40"], "product_category": ["kombucha", "irn bru"]}, {"customer_id": "C96", "loyalty_score": 10, "purchase_count": 3, "product_id": ["P38", "P35", "P38"], "product_category": ["kombucha", "carrot cake", "kombucha"]}, {"customer_id": "C101", "loyalty_score": 2, "purchase_count": 1, "product_id": ["P45"], "product_category": ["hummus"]}, {"customer_id": "C109", "loyalty_score": 6, "purchase_count": 2, "product_id": ["P58", "P49"], "product_category": ["coconut water", "smoked salmon"]}, {"customer_id": "C119", "loyalty_score": 7, "purchase_count": 3, "product_id": ["P61", "P62", "P63"], "product_category": ["red wine", "gin", "cognac"]}, {"customer_id": "C125", "loyalty_score": 1, "purchase_count": 3, "product_id": ["P52", "P56", "P56"], "product_category": ["oats", "greek yoghurt", "greek yoghurt"]}, {"customer_id": "C126", "loyalty_score": 4, "purchase_count": 2, "product_id": ["P35", "P36"], "product_category": ["carrot cake", "salted caramel dark chocolate"]}, {"customer_id": "C128", "loyalty_score": 5, "purchase_count": 3, "product_id": ["P33", "P32", "P30"], "product_category": ["apples", "onions", "mango"]}, {"customer_id": "C133", "loyalty_score": 3, "purchase_count": 1, "product_id": ["P55"], "product_category": ["lentil soup"]}, {"customer_id": "C136", "loyalty_score": 10, "purchase_count": 2, "product_id": ["P18", "P18"], "product_category": ["men's striped socks", "men's striped socks"]}, {"customer_id": "C137", "loyalty_score": 9, "purchase_count": 3, "product_id": ["P02", "P08", "P07"], "product_category": ["kitchen roll", "aluminium foil", "cling film"]}]